LICENSE
MANIFEST.in
README.rst
requirements.txt
setup.cfg
setup.py
topobot/__init__.py
topobot/cmd.py
topobot/constants.py
topobot/functions.py
topobot/plugin.py
topobot.egg-info/PKG-INFO
topobot.egg-info/SOURCES.txt
topobot.egg-info/dependency_links.txt
topobot.egg-info/entry_points.txt
topobot.egg-info/not-zip-safe
topobot.egg-info/requires.txt
topobot.egg-info/top_level.txt