Metadata-Version: 1.0
Name: topobot
Version: 1.0.0
Summary: TopoBot - AREDN Mesh Topography Bot.
Home-page: https://github.com/ampledata/topobot
Author: Greg Albrecht
Author-email: oss@undef.net
License: Copyright 2018 Greg Albrecht
